transformer_encoder/__init__.py
transformer_encoder/encoder.py
transformer_encoder/encoder_layer.py
transformer_encoder/feed_forward.py
transformer_encoder/layer_norm.py
transformer_encoder/multi_head_attention.py
transformer_encoder/utils/__init__.py
transformer_encoder/utils/positional_encoding.py
transformer_encoder/utils/warmup_optimizer.py
transformer_encoder-0.0.3.dist-info/LICENSE
transformer_encoder-0.0.3.dist-info/METADATA
transformer_encoder-0.0.3.dist-info/WHEEL
transformer_encoder-0.0.3.dist-info/top_level.txt
transformer_encoder-0.0.3.dist-info/RECORD
