Metadata-Version: 2.1
Name: transformer-encoder
Version: 0.0.3
Summary: A pytorch implementation of transformer encoder
Home-page: https://github.com/guocheng2018/transformer-encoder
Author: Cheng Guo
Author-email: guocheng672@gmail.com
License: UNKNOWN
Platform: UNKNOWN
Classifier: Programming Language :: Python :: 3
Classifier: License :: OSI Approved :: MIT License
Classifier: Operating System :: OS Independent
Requires-Python: >=3.5
